{
  "id": "b61813384c59f973",
  "type": "ai-news",
  "title": "6月15日振込分から増額！申請しないと0円「年金生活者支援給付金」はいくら年金に上乗せされる？2026年度は前年度比3.2％引き上げ",
  "date": "2026-06-13",
  "playlist": "",
  "url": "https://limo.media/articles/-/126320",
  "path": "AI-News/2026-06-13_6月15日振込分から増額！申請しないと0円「年金生活者支援給付金」はいくら年金に上乗せされる？2026年度は前年度比3.2％引き上げ_1747008985.md",
  "updated_at": "2026-06-13T22:18:35",
  "content": "---\ntype: \"ai-news\"\ndate: \"2026-06-13\"\nurl: \"https://limo.media/articles/-/126320\"\nsource: \"raindrop-discord-summary-send\"\nraindrop_id: \"1747008985\"\nstatus: \"success\"\ntags:\n  - \"ai-news\"\n  - \"article\"\n  - \"raindrop\"\n---\n\n# 6月15日振込分から増額！申請しないと0円「年金生活者支援給付金」はいくら年金に上乗せされる？2026年度は前年度比3.2％引き上げ\n\n- URL: https://limo.media/articles/-/126320\n- Raindrop ID: 1747008985\n- status: success\n\n【Raindrop要約】\nタイトル：\n6月15日振込分から増額！申請しないと0円「年金生活者支援給付金」はいくら年金に上乗せされる？2026年度は前年度比3.2％引き上げ\nURL：\nhttps://limo.media/articles/-/126320\n\n概要：\n- 公的年金に上乗せして支給される「年金生活者支援給付金」について、2026年度の最新情報を解説した記事。\n- 対象は、公的年金等の収入やその他所得が基準額に満たない年金受給者（主に住民税非課税世帯）。\n- 老齢・障害・遺族の3種類があり、2026年度は前年度比3.2％引き上げ、6月15日振込分から増額。\n- 申請しなければ受け取れない（0円）ため、封筒の色（緑・薄緑・薄橙）に応じた手続きが必要。\n- 要件を満たす限り、2カ月に1度継続的に支給される。\n\n自分に使えそうなポイント：\n- 申請が必要という点は見落とされやすく、「知らないと損する制度」として発信ネタになりうる\n- 封筒の色で手続きが異なる仕組みは、整理して伝えると読者の役に立つ情報\n- 毎年度改定される給付額は、年金関連コンテンツの更新ネタとして定期的に使える\n\n参考にすべき点：\n- 出所が厚生労働省の公式資料であり、制度の信頼性は高い\n- 対象者・支給額・手続き方法という構成は、制度解説記事の基本フォーマットとして参考になる\n\n要確認：\n- 2026年度の具体的な給付額（一覧）が本文抜粋に含まれておらず、実際の金額は未確認\n- 所得基準額の具体的な数値も本文から読み取れないため、詳細は厚生労働省の原典を確認する必要がある\n- 繰上げ受給者（薄橙封筒）向けの手続き詳細も記事内で説明されているが、抜粋には含まれていない\n\n分類候補：\n発信ネタ / あとで深掘り\n\n取得状態：\n本文取得成功\n"
}
